ring/__init__.py
ring/algebra.py
ring/base.py
ring/maths.py
ring/spatial.py
ring/algorithms/__init__.py
ring/algorithms/_random.py
ring/algorithms/dynamics.py
ring/algorithms/jcalc.py
ring/algorithms/kinematics.py
ring/algorithms/sensors.py
ring/algorithms/custom_joints/__init__.py
ring/algorithms/custom_joints/rr_imp_joint.py
ring/algorithms/custom_joints/rr_joint.py
ring/algorithms/custom_joints/rsaddle_joint.py
ring/algorithms/custom_joints/suntay.py
ring/algorithms/generator/__init__.py
ring/algorithms/generator/base.py
ring/algorithms/generator/batch.py
ring/algorithms/generator/finalize_fns.py
ring/algorithms/generator/motion_artifacts.py
ring/algorithms/generator/pd_control.py
ring/algorithms/generator/setup_fns.py
ring/algorithms/generator/types.py
ring/extras/__init__.py
ring/extras/backend.py
ring/extras/colab.py
ring/extras/dataloader.py
ring/extras/dataloader_torch.py
ring/extras/hdf5.py
ring/extras/interactive_viewer.py
ring/extras/normalizer.py
ring/extras/randomize_sys.py
ring/extras/torch_loss_fn.py
ring/extras/register_gym_envs/__init__.py
ring/extras/register_gym_envs/saddle.py
ring/io/__init__.py
ring/io/examples.py
ring/io/test_examples.py
ring/io/examples/branched.xml
ring/io/examples/inv_pendulum.xml
ring/io/examples/knee_flexible_imus.xml
ring/io/examples/spherical_stiff.xml
ring/io/examples/symmetric.xml
ring/io/examples/test_all_1.xml
ring/io/examples/test_all_2.xml
ring/io/examples/test_ang0_pos0.xml
ring/io/examples/test_control.xml
ring/io/examples/test_double_pendulum.xml
ring/io/examples/test_free.xml
ring/io/examples/test_kinematics.xml
ring/io/examples/test_randomize_position.xml
ring/io/examples/test_sensors.xml
ring/io/examples/test_three_seg_seg2.xml
ring/io/examples/exclude/knee_trans_dof.xml
ring/io/examples/exclude/standard_sys.xml
ring/io/examples/exclude/standard_sys_rr_imp.xml
ring/io/examples/test_morph_system/four_seg_seg1.xml
ring/io/examples/test_morph_system/four_seg_seg3.xml
ring/io/xml/__init__.py
imt_ring-1.7.1.dist-info/METADATA
imt_ring-1.7.1.dist-info/WHEEL
imt_ring-1.7.1.dist-info/entry_points.txt
imt_ring-1.7.1.dist-info/top_level.txt
imt_ring-1.7.1.dist-info/RECORD
