Metadata-Version: 2.4
Name: imt-ring
Version: 1.7.1
Summary: RING: Recurrent Inertial Graph-based Estimator
Author-email: Simon Bachhuber <simon.bachhuber@fau.de>
Project-URL: Homepage, https://github.com/SimiPixel/ring
Project-URL: Issues, https://github.com/SimiPixel/ring/issues
Classifier: Programming Language :: Python :: 3
Classifier: License :: OSI Approved :: MIT License
Classifier: Operating System :: OS Independent
Requires-Python: >=3.10
Requires-Dist: jaxlib
Requires-Dist: jax
Requires-Dist: jaxopt
Requires-Dist: numpy
Requires-Dist: flax
Requires-Dist: tqdm
Requires-Dist: imt-tree-utils
Requires-Dist: wandb
Requires-Dist: optax
Requires-Dist: dm-haiku
Requires-Dist: pyyaml
Provides-Extra: dev
Requires-Dist: mkdocs; extra == "dev"
Requires-Dist: mkdocs-material; extra == "dev"
Requires-Dist: mkdocstrings; extra == "dev"
Requires-Dist: mkdocstrings-python; extra == "dev"
Requires-Dist: mknotebooks; extra == "dev"
Requires-Dist: pytest; extra == "dev"
Requires-Dist: pytest-xdist; extra == "dev"
Requires-Dist: nbmake; extra == "dev"
